MANIFEST.in
NEWS.rst
README.rst
setup.py
tokenizertools.py
docs/UserManual.rst
tests/__init__.py
tests/test_tokenizertools.py
tokenizertools.egg-info/PKG-INFO
tokenizertools.egg-info/SOURCES.txt
tokenizertools.egg-info/dependency_links.txt
tokenizertools.egg-info/top_level.txt