Metadata-Version: 1.0
Name: tokenizertools
Version: 0.1a
Summary: Implements lexical analyzers as iterators yielding tokens.
Home-page: http://github.com/dbc/tokenizertools
Author: David B. Curtis
Author-email: davecurtis@sonic.net
License: BSD
Platform: any
